cloudmol/__init__.py
cloudmol/cloudmol.py
cloudmol/fold_batch.py
cloudmol/utils/__init__.py
cloudmol/utils/plot_utils.py
cloudmol-0.1.3.dist-info/LICENSE
cloudmol-0.1.3.dist-info/METADATA
cloudmol-0.1.3.dist-info/WHEEL
cloudmol-0.1.3.dist-info/entry_points.txt
cloudmol-0.1.3.dist-info/top_level.txt
cloudmol-0.1.3.dist-info/RECORD
