Metadata-Version: 2.1
Name: cloudmol
Version: 0.1.3
Summary: Easily protein folding and design with cloudmol
Home-page: https://github.com/JinyuanSun/PymolFold
Author: Jinyuan Sun
Author-email: jinyuansun98@gmail.com
Requires-Python: >=3.6
License-File: LICENSE
Requires-Dist: requests
Requires-Dist: numpy
Requires-Dist: matplotlib
Requires-Dist: biopython
